pyecharts_json_render/__init__.py
pyecharts_json_render/render.py
pyecharts_json_render-0.0.3.dist-info/LICENSE
pyecharts_json_render-0.0.3.dist-info/METADATA
pyecharts_json_render-0.0.3.dist-info/WHEEL
pyecharts_json_render-0.0.3.dist-info/top_level.txt
pyecharts_json_render-0.0.3.dist-info/RECORD
