Metadata-Version: 2.1
Name: pyecharts-json-render
Version: 0.0.3
Summary: A simple wrapper using pyecharts to render html from Echarts option(JSON).
Home-page: https://github.com/forhonourlx/pyecharts_json_render
Author: forhonourlx
Author-email: forhonourlx@qq.com
Classifier: Programming Language :: Python :: 3
Classifier: License :: OSI Approved :: MIT License
Classifier: Operating System :: OS Independent
License-File: LICENSE
Requires-Dist: pyecharts (<=1.5.1)
Requires-Dist: Jinja2 (<=3.0.3)
Requires-Dist: beautifulsoup4
